LICENSE
MANIFEST.in
README.md
setup.py
ledtable/LEDMatrix.py
ledtable/SerialLEDTable.py
ledtable/__init__.py
ledtable/tkLEDTable.py
ledtable.egg-info/PKG-INFO
ledtable.egg-info/SOURCES.txt
ledtable.egg-info/dependency_links.txt
ledtable.egg-info/requires.txt
ledtable.egg-info/top_level.txt