Metadata-Version: 1.1
Name: ledtable
Version: 0.0.2
Summary: Python library to control and show led tables.
Home-page: https://github.com/niccokunzmann/ledtable
Author: Nicco Kunzmann
Author-email: niccokunzmann@rambler.ru
License: MIT
Keywords: arduino led stipe
Platform: UNKNOWN
Classifier: Development Status :: 4 - Beta
Classifier: Intended Audience :: Developers
Classifier: License :: OSI Approved :: MIT License
Classifier: Topic :: Software Development :: Libraries :: Python Modules
